cdklabs/cdk_atmosphere_service/__init__.py
cdklabs/cdk_atmosphere_service/py.typed
cdklabs/cdk_atmosphere_service/_jsii/__init__.py
cdklabs/cdk_atmosphere_service/_jsii/cdk-atmosphere-service@0.0.9.jsii.tgz
cdklabs.cdk_atmosphere_service-0.0.9.dist-info/LICENSE
cdklabs.cdk_atmosphere_service-0.0.9.dist-info/METADATA
cdklabs.cdk_atmosphere_service-0.0.9.dist-info/WHEEL
cdklabs.cdk_atmosphere_service-0.0.9.dist-info/top_level.txt
cdklabs.cdk_atmosphere_service-0.0.9.dist-info/RECORD
